flake8_cgx/__init__.py
flake8_cgx/patch.py
flake8_cgx/plugin.py
flake8_cgx-0.1.0.dist-info/entry_points.txt
flake8_cgx-0.1.0.dist-info/LICENSE
flake8_cgx-0.1.0.dist-info/WHEEL
flake8_cgx-0.1.0.dist-info/METADATA
flake8_cgx-0.1.0.dist-info/RECORD
